krate/__init__.py
krate-0.0.1.dist-info/LICENSE
krate-0.0.1.dist-info/METADATA
krate-0.0.1.dist-info/WHEEL
krate-0.0.1.dist-info/top_level.txt
krate-0.0.1.dist-info/RECORD
