Metadata-Version: 2.1
Name: krate
Version: 0.0.1
Summary: All things data.
Home-page: https://github.com/BenedictWilkinsAI/krate
Author: Benedict Wilkins
Author-email: brjw@hotmail.co.uk
License: GNU3
Platform: UNKNOWN
Classifier: Programming Language :: Python :: 3
Classifier: Operating System :: OS Independent
